light_ass/__init__.py
light_ass/constants.py
light_ass/events.py
light_ass/script_info.py
light_ass/styles.py
light_ass/subtitle.py
light_ass/tag_parser.py
light_ass/utils.py
light_ass/ass_types/__init__.py
light_ass/ass_types/ass_alpha.py
light_ass/ass_types/ass_color.py
light_ass/ass_types/ass_time.py
light_ass/shape/__init__.py
light_ass/shape/curve.py
light_ass/shape/point.py
light_ass/shape/segment.py
light_ass/shape/shape.py
light_ass-0.1.4.dist-info/licenses/LICENSE
light_ass-0.1.4.dist-info/METADATA
light_ass-0.1.4.dist-info/WHEEL
light_ass-0.1.4.dist-info/top_level.txt
light_ass-0.1.4.dist-info/RECORD
