Metadata-Version: 2.4
Name: light-ass
Version: 0.1.4
Summary: A lightweight library for handling ASS subtitles
Author-email: Oborozuki <oborozuk1@qq.com>
License: MIT License
Project-URL: Homepage, https://github.com/oborozuk1/light-ass
Project-URL: Repository, https://github.com/oborozuk1/light-ass.git
Project-URL: Bug Tracker, https://github.com/oborozuk1/light-ass/issues
Keywords: subtitle,ass
Classifier: Programming Language :: Python :: 3
Classifier: License :: OSI Approved :: MIT License
Classifier: Operating System :: OS Independent
Classifier: Topic :: Multimedia :: Video
Classifier: Development Status :: 3 - Alpha
Classifier: Topic :: Software Development :: Libraries :: Python Modules
Requires-Python: >=3.12
License-File: LICENSE
Dynamic: license-file
